README.md
setup.py
stg/__init__.py
stg/io.py
stg/layers.py
stg/losses.py
stg/matching.py
stg/meter.py
stg/models.py
stg/stg.py
stg/utils.py
stg.egg-info/PKG-INFO
stg.egg-info/SOURCES.txt
stg.egg-info/dependency_links.txt
stg.egg-info/not-zip-safe
stg.egg-info/requires.txt
stg.egg-info/top_level.txt