Metadata-Version: 2.1
Name: stg
Version: 0.1.1
Summary: feature selection using stochastic gates
Home-page: https://github.com/runopti/stg
Author: Yutaro Yamada
Author-email: yutaro.yamada@yale.edu
License: MIT
Platform: UNKNOWN
